aoquality/__init__.py
aoquality/aoquality.py
aoquality/tools/aostats.py
aoquality-0.2.6.dist-info/LICENSE
aoquality-0.2.6.dist-info/METADATA
aoquality-0.2.6.dist-info/WHEEL
aoquality-0.2.6.dist-info/entry_points.txt
aoquality-0.2.6.dist-info/RECORD
