Metadata-Version: 2.1
Name: aoquality
Version: 0.2.6
Summary: Python module to access Measurement Sets' quality statistics produced by aoflagger, aoquality or DPPP.
Home-page: https://gitlab.com/flomertens/aoquality/
License: GPL-3.0-or-later
Author: "Florent Mertens"
Author-email: "florent.mertens@gmail.com"
Requires-Python: >=3.7,<4.0
Classifier: License :: OSI Approved :: GNU General Public License v3 or later (GPLv3+)
Classifier: Programming Language :: Python :: 3
Classifier: Programming Language :: Python :: 3.7
Classifier: Programming Language :: Python :: 3.8
Classifier: Programming Language :: Python :: 3.9
Classifier: Programming Language :: Python :: 3.10
Classifier: Programming Language :: Python :: 3.11
Classifier: Programming Language :: Python :: 3.12
Requires-Dist: click (>=7.0,<9.0)
Requires-Dist: importlib-metadata (>=1.0,<2.0) ; python_version < "3.8"
Requires-Dist: matplotlib (>=3.0,<4.0)
Requires-Dist: python-casacore (>=3.0,<4.0)
Project-URL: Repository, https://gitlab.com/flomertens/aoquality/
